{
    "apiNodePort": 3001,
    "endpoints": {
        "marketData": "https://min-api.cryptocompare.com/",
        "statisticsService": "https://service.test.siamreiwa.com"
    },
    "networkConfig": {
        "namespaceName": "canade.cbdp",
        "namespaceId": "5282230404218E56",
        "divisibility": "6"
    },
    "footer": {
        "link": [
            {
                "href": "https://github.com/siamreiwa",
                "text": "Github",
                "icon": "IconGithub"
            },
            {
                "href": "#",
                "text": "Discord",
                "icon": "IconDiscord"
            },
            {
                "href": "https://twitter.com/taimadonya",
                "text": "Twitter",
                "icon": "IconTwitter"
            },
            {
                "href": "https://faucet.test.siamreiwa.com/",
                "text": "Faucet",
                "icon": "IconCurrencyUsd"
            }
        ]
    },
    "timezone": "Local"
}
